LICENSE
README.md
setup.py
jjb_discord/__init__.py
jjb_discord/discord_notifier.py
jjb_discord.egg-info/PKG-INFO
jjb_discord.egg-info/SOURCES.txt
jjb_discord.egg-info/dependency_links.txt
jjb_discord.egg-info/entry_points.txt
jjb_discord.egg-info/requires.txt
jjb_discord.egg-info/top_level.txt