Metadata-Version: 2.1
Name: jjb-discord
Version: 0.0.dev1680284036
Summary: Jenkins Job Builder Discord Notifier
Home-page: https://github.com/ettoreleandrotognoli/jjb-discord
Download-URL: https://github.com/ettoreleandrotognoli/jjb-discord/tree/v0.0.dev1680284036/
Author: Ettore Leandro Tognoli
Author-email: ettoreleandrotognoli@gmail.com
License: Apache License 2.0
Classifier: Environment :: Console
Classifier: Intended Audience :: Developers
Classifier: Intended Audience :: Information Technology
Classifier: License :: OSI Approved :: Apache Software License
Classifier: Operating System :: OS Independent
Classifier: Programming Language :: Python
Classifier: Programming Language :: Python :: 2
Classifier: Programming Language :: Python :: 3
License-File: LICENSE
